{
  "meta": {
    "stableOrder": true
  },
  "lockfileVersion": 3,
  "ATTENTION": "THIS IS AN AUTOGENERATED FILE. DO NOT EDIT THIS FILE DIRECTLY.",
  "specifiers": {
    "@hzw/common_library@../../library/common_library": "@hzw/common_library@../../library/common_library",
    "common_library@../../library/common_library": "common_library@../../library/common_library",
    "hara@../../harA": "hara@../../harA",
    "harb@../../harB": "harb@../../harB",
    "hspc@../../hspC": "hspc@../../hspC",
    "routerapi@../../RouterApi": "routerapi@../../RouterApi"
  },
  "packages": {
    "@hzw/common_library@../../library/common_library": {
      "name": "common_library",
      "version": "1.0.0",
      "resolved": "../../library/common_library",
      "registryType": "local"
    },
    "common_library@../../library/common_library": {
      "name": "common_library",
      "version": "1.0.0",
      "resolved": "../../library/common_library",
      "registryType": "local"
    },
    "hara@../../harA": {
      "name": "hara",
      "version": "1.0.0",
      "resolved": "../../harA",
      "registryType": "local",
      "dependencies": {
        "routerapi": "file:../RouterApi",
        "common_library": "file:../library/common_library"
      }
    },
    "harb@../../harB": {
      "name": "harb",
      "version": "1.0.0",
      "resolved": "../../harB",
      "registryType": "local",
      "dependencies": {
        "routerapi": "file:../RouterApi"
      }
    },
    "hspc@../../hspC": {
      "name": "hspc",
      "version": "1.0.0",
      "resolved": "../../hspC",
      "registryType": "local",
      "dependencies": {
        "routerapi": "file:../RouterApi"
      },
      "packageType": "InterfaceHar"
    },
    "routerapi@../../RouterApi": {
      "name": "@hzw/zrouter",
      "version": "1.0.8",
      "resolved": "../../RouterApi",
      "registryType": "local"
    }
  }
}