{
  "meta": {
    "stableOrder": true
  },
  "lockfileVersion": 3,
  "ATTENTION": "THIS IS AN AUTOGENERATED FILE. DO NOT EDIT THIS FILE DIRECTLY.",
  "specifiers": {
    "@hzw/zrouter@^1.0.0": "@hzw/zrouter@1.0.0"
  },
  "packages": {
    "@hzw/zrouter@1.0.0": {
      "name": "@hzw/zrouter",
      "version": "1.0.0",
      "integrity": "sha512-8LmJ6arLPzi18sirTOo6a5CUKRz+L3ndGNMdKa22OQPuWUpnI7AxtYah5uiiafA6eM/g9gjsYo1H7btZ6FAvEA==",
      "resolved": "https://ohpm.openharmony.cn/ohpm/@hzw/zrouter/-/zrouter-1.0.0.har",
      "registryType": "ohpm"
    }
  }
}